_pywhispercpp.cpython-311-x86_64-linux-gnu.so
libwhisper.so
pywhispercpp/__init__.py
pywhispercpp/_logger.py
pywhispercpp/constants.py
pywhispercpp/model.py
pywhispercpp/utils.py
cotipywhispercpp-1.1.1.dist-info/LICENSE
cotipywhispercpp-1.1.1.dist-info/METADATA
cotipywhispercpp-1.1.1.dist-info/WHEEL
cotipywhispercpp-1.1.1.dist-info/entry_points.txt
cotipywhispercpp-1.1.1.dist-info/top_level.txt
cotipywhispercpp-1.1.1.dist-info/RECORD
