Metadata-Version: 2.1
Name: cotipywhispercpp
Version: 1.1.1
Summary: Python bindings for whisper.cpp
Author: abdeladim-s
License: MIT
Project-URL: Documentation, https://abdeladim-s.github.io/pywhispercpp/
Project-URL: Source, https://github.com/abdeladim-s/pywhispercpp
Project-URL: Tracker, https://github.com/abdeladim-s/pywhispercpp/issues
Requires-Python: >=3.8
License-File: LICENSE
Requires-Dist: numpy
Requires-Dist: pydub
Requires-Dist: requests
Requires-Dist: tqdm
Requires-Dist: platformdirs
Provides-Extra: examples
Requires-Dist: sounddevice ; extra == 'examples'
Requires-Dist: webrtcvad ; extra == 'examples'
